Metadata-Version: 2.1
Name: mpl-plotter
Version: 3.9.2
Summary: Matplotlib-based plotting library
Home-page: https://github.com/antonlopezr/mpl_plotter
Author: Antonio Lopez Rivera
Author-email: antonlopezr99@gmail.com
License: UNKNOWN
Platform: UNKNOWN
Classifier: Programming Language :: Python :: 3
Classifier: License :: OSI Approved :: MIT License
Classifier: Operating System :: OS Independent
Requires-Python: >=3.6
Requires-Dist: numpy
Requires-Dist: matplotlib
Requires-Dist: scikit-image
Requires-Dist: termcolor
Requires-Dist: pandas
Requires-Dist: PyQt5
Requires-Dist: Python-Alexandria
Requires-Dist: coverage
Requires-Dist: coverage-badge
